movis/__init__.py
movis/attribute.py
movis/enum.py
movis/imgproc.py
movis/motion.py
movis/ops.py
movis/py.typed
movis/subtitle.py
movis/transform.py
movis/util.py
movis/contrib/__init__.py
movis/contrib/presentation.py
movis/contrib/segmentation.py
movis/contrib/voicevox.py
movis/effect/__init__.py
movis/effect/blur.py
movis/effect/color.py
movis/effect/protocol.py
movis/effect/style.py
movis/layer/__init__.py
movis/layer/composition.py
movis/layer/drawing.py
movis/layer/layer_ops.py
movis/layer/media.py
movis/layer/mixin.py
movis/layer/protocol.py
movis/layer/texture.py
movis-0.7.1.dist-info/LICENSE
movis-0.7.1.dist-info/METADATA
movis-0.7.1.dist-info/WHEEL
movis-0.7.1.dist-info/top_level.txt
movis-0.7.1.dist-info/RECORD
