Metadata-Version: 2.1
Name: movis
Version: 0.7.1
Summary: A video editing library
Home-page: https://github.com/rezoo/movis
Author: Masaki Saito
Author-email: msaito@preferred.jp
License: MIT License
Project-URL: Source, https://github.com/rezoo/movis
Keywords: video video-processing video-editing
Classifier: License :: OSI Approved :: MIT License
Classifier: Operating System :: OS Independent
Classifier: Programming Language :: Python
Classifier: Programming Language :: Python :: 3.9
Classifier: Programming Language :: Python :: 3.10
Classifier: Programming Language :: Python :: 3.11
Classifier: Programming Language :: Python :: 3.12
Requires-Python: >=3.9.0
License-File: LICENSE
Requires-Dist: numpy >=1.18.1
Requires-Dist: librosa >=0.10.1
Requires-Dist: Pillow >=8.2.0
Requires-Dist: imageio >=2.31.1
Requires-Dist: imageio-ffmpeg >=0.4.8
Requires-Dist: tqdm >=4.46.0
Requires-Dist: diskcache >=5.6.1
Requires-Dist: opencv-python >=4.8.0
Requires-Dist: PySide6 >=6.5.2
